[{"_key":"12018727","_id":"progs/12018727","_from":"consensus_goals/8010765","_to":"consensus_goals/8010769","_rev":"_bBee8aq--_","label":"1a","weight":0.5,"left":8010765,"right":8010769,"id":12018727},{"_key":"12018748","_id":"progs/12018748","_from":"consensus_goals/8010771","_to":"consensus_goals/12018663","_rev":"_bBee8aq--B","label":"1f","weight":0.5,"left":8010771,"right":12018663,"id":12018748},{"_key":"12018757","_id":"progs/12018757","_from":"consensus_goals/8010767","_to":"consensus_goals/8010768","_rev":"_bBee8aq--D","label":"1c","weight":0.5,"left":8010767,"right":8010768,"id":12018757},{"_key":"12018769","_id":"progs/12018769","_from":"consensus_goals/8010768","_to":"consensus_goals/12018663","_rev":"_bBee8aq--F","label":"1e","weight":0.5,"left":8010768,"right":12018663,"id":12018769},{"_key":"12018782","_id":"progs/12018782","_from":"consensus_goals/8010768","_to":"consensus_goals/8010769","_rev":"_bBee8aq--H","label":"1d","weight":0.5,"left":8010768,"right":8010769,"id":12018782},{"_key":"12018803","_id":"progs/12018803","_from":"consensus_goals/8010772","_to":"consensus_goals/8010773","_rev":"_bBee8aq--J","label":"1b","weight":0.5,"left":8010772,"right":8010773,"id":12018803},{"_key":"12018894","_id":"progs/12018894","_from":"consensus_goals/8010763","_to":"consensus_goals/8010764","_rev":"_bBee8aq--L","label":"2a","weight":0.5,"left":8010763,"right":8010764,"id":12018894},{"_key":"12018897","_id":"progs/12018897","_from":"consensus_goals/8010763","_to":"consensus_goals/8010766","_rev":"_bBee8aq--N","label":"2b","weight":0.5,"left":8010763,"right":8010766,"id":12018897},{"_key":"12018900","_id":"progs/12018900","_from":"consensus_goals/8010763","_to":"consensus_goals/8010767","_rev":"_bBee8aq--P","label":"2c","weight":0.5,"left":8010763,"right":8010767,"id":12018900},{"_key":"12018903","_id":"progs/12018903","_from":"consensus_goals/8010764","_to":"consensus_goals/8010765","_rev":"_bBee8aq--R","label":"2d","weight":0.5,"left":8010764,"right":8010765,"id":12018903},{"_key":"12018908","_id":"progs/12018908","_from":"consensus_goals/8010765","_to":"consensus_goals/8010773","_rev":"_bBee8aq--T","label":"2e","weight":0.5,"left":8010765,"right":8010773,"id":12018908},{"_key":"12018964","_id":"progs/12018964","_from":"consensus_goals/8010766","_to":"consensus_goals/8010768","_rev":"_bBee8aq--V","label":"3a","weight":0.5,"left":8010766,"right":8010768,"id":12018964},{"_key":"12019015","_id":"progs/12019015","_from":"consensus_goals/8010769","_to":"consensus_goals/8010773","_rev":"_bBee8aq--X","label":"3b","weight":0.5,"left":8010769,"right":8010773,"id":12019015},{"_key":"12019020","_id":"progs/12019020","_from":"consensus_goals/8010769","_to":"consensus_goals/8010774","_rev":"_bBee8aq--Z","label":"3d","weight":0.5,"left":8010769,"right":8010774,"id":12019020},{"_key":"12019027","_id":"progs/12019027","_from":"consensus_goals/12018663","_to":"consensus_goals/8010774","_rev":"_bBee8aq--b","label":"3e","weight":0.5,"left":12018663,"right":8010774,"id":12019027},{"_key":"12019030","_id":"progs/12019030","_from":"consensus_goals/8010774","_to":"consensus_goals/8010773","_rev":"_bBee8aq--d","label":"3f","weight":0.5,"left":8010774,"right":8010773,"id":12019030},{"_key":"12019336","_id":"progs/12019336","_from":"consensus_goals/8010766","_to":"consensus_goals/8010771","_rev":"_bBee8aq--f","label":"4a","weight":0.5,"left":8010766,"right":8010771,"id":12019336},{"_key":"12019457","_id":"progs/12019457","_from":"consensus_goals/8010769","_to":"consensus_goals/8010772","_rev":"_bBee8aq--h","label":"3c","weight":0.5,"left":8010769,"right":8010772,"id":12019457},{"_key":"12019483","_id":"progs/12019483","_from":"consensus_goals/12019468","_to":"consensus_goals/8010763","_rev":"_bBee8aq--j","label":"entry a","weight":0.5,"left":12019468,"right":8010763,"id":12019483},{"_key":"12019488","_id":"progs/12019488","_from":"consensus_goals/12019468","_to":"consensus_goals/12019129","_rev":"_bBee8aq--l","label":"entry b","weight":0.5,"left":12019468,"right":12019129,"id":12019488},{"_key":"12019538","_id":"progs/12019538","_from":"consensus_goals/12019129","_to":"consensus_goals/8010769","_rev":"_bBee8aq--n","weight":0.5,"left":12019129,"right":8010769,"label":"4b","id":12019538},{"_key":"12019543","_id":"progs/12019543","_from":"consensus_goals/12019129","_to":"consensus_goals/8010771","_rev":"_bBee8aq--p","weight":0.5,"left":12019129,"right":8010771,"label":"4c","id":12019543}]